danbooru_tag_expander/__init__.py
danbooru_tag_expander/tag_expander_cli.py
danbooru_tag_expander/utils/__init__.py
danbooru_tag_expander/utils/tag_expander.py
danbooru_tag_expander-0.2.7.dist-info/licenses/LICENSE
danbooru_tag_expander-0.2.7.dist-info/METADATA
danbooru_tag_expander-0.2.7.dist-info/WHEEL
danbooru_tag_expander-0.2.7.dist-info/entry_points.txt
danbooru_tag_expander-0.2.7.dist-info/top_level.txt
danbooru_tag_expander-0.2.7.dist-info/RECORD
