Metadata-Version: 2.4
Name: danbooru-tag-expander
Version: 0.2.7
Summary: A tool for expanding Danbooru tags with their implications and aliases
Author-email: Allen Day <allenday@users.github.com>
Maintainer-email: Allen Day <allenday@users.github.com>
License-Expression: MIT
Project-URL: Homepage, https://github.com/allenday/danbooru-tag-expander
Project-URL: Documentation, https://github.com/allenday/danbooru-tag-expander#readme
Project-URL: Repository, https://github.com/allenday/danbooru-tag-expander.git
Project-URL: Bug Tracker, https://github.com/allenday/danbooru-tag-expander/issues
Project-URL: Changelog, https://github.com/allenday/danbooru-tag-expander/releases
Keywords: danbooru,tags,image,tagging,api,booru
Classifier: Development Status :: 3 - Alpha
Classifier: Intended Audience :: Developers
Classifier: Operating System :: OS Independent
Classifier: Programming Language :: Python :: 3
Classifier: Programming Language :: Python :: 3.6
Classifier: Programming Language :: Python :: 3.7
Classifier: Programming Language :: Python :: 3.8
Classifier: Programming Language :: Python :: 3.9
Classifier: Programming Language :: Python :: 3.10
Classifier: Programming Language :: Python :: 3.11
Classifier: Programming Language :: Python :: 3.12
Classifier: Topic :: Internet :: WWW/HTTP :: Dynamic Content
Classifier: Topic :: Software Development :: Libraries :: Python Modules
Classifier: Topic :: Multimedia :: Graphics
Requires-Python: >=3.6
License-File: LICENSE
Requires-Dist: python-dotenv>=0.19.0
Requires-Dist: requests>=2.26.0
Requires-Dist: tqdm>=4.62.0
Requires-Dist: pybooru>=4.2.2
Requires-Dist: danbooru-tag-graph>=0.2.2
Provides-Extra: dev
Requires-Dist: pytest>=6.0; extra == "dev"
Requires-Dist: pytest-cov>=2.10.0; extra == "dev"
Requires-Dist: black>=21.0.0; extra == "dev"
Requires-Dist: flake8>=3.8.0; extra == "dev"
Requires-Dist: mypy>=0.800; extra == "dev"
Requires-Dist: build>=0.7.0; extra == "dev"
Requires-Dist: twine>=3.0.0; extra == "dev"
Provides-Extra: test
Requires-Dist: pytest>=6.0; extra == "test"
Requires-Dist: pytest-cov>=2.10.0; extra == "test"
Dynamic: license-file
